perceptron/Perceptron.py
perceptron/__init__.py
perceptronPackaging_VeluruBhanuprakash-0.0.4.dist-info/LICENSE
perceptronPackaging_VeluruBhanuprakash-0.0.4.dist-info/METADATA
perceptronPackaging_VeluruBhanuprakash-0.0.4.dist-info/WHEEL
perceptronPackaging_VeluruBhanuprakash-0.0.4.dist-info/top_level.txt
perceptronPackaging_VeluruBhanuprakash-0.0.4.dist-info/RECORD
