Metadata-Version: 2.1
Name: perceptronPackaging-VeluruBhanuprakash
Version: 0.0.4
Summary: A small package of perceptron
Home-page: https://github.com/VeluruBhanuprakash/perceptronPackaging
Author: VeluruBhanuprakash
Author-email: bhanuprakash@gmail.com
License: UNKNOWN
Project-URL: Bug Tracker, https://github.com/VeluruBhanuprakash/perceptronPackaging/issues
Platform: UNKNOWN
Classifier: Programming Language :: Python :: 3
Classifier: License :: OSI Approved :: MIT License
Classifier: Operating System :: OS Independent
Requires-Python: >=3.6
License-File: LICENSE
Requires-Dist: numpy
Requires-Dist: joblib
Requires-Dist: pandas
